{
 "points": [
  {
   "coordinates": [
    0.32488677564483476,
    0.8592697453439551
   ],
   "class": 1.0,
   "name": "point1"
  },
  {
   "coordinates": [
    0.1650809093593439,
    0.24427633929984202
   ],
   "class": 1.0,
   "name": "point2"
  },
  {
   "coordinates": [
    0.14675268540465228,
    0.8594016353333529
   ],
   "class": 1.0,
   "name": "point3"
  },
  {
   "coordinates": [
    0.27270957720246836,
    0.70433717376134
   ],
   "class": 1.0,
   "name": "point4"
  },
  {
   "coordinates": [
    0.2972425736643297,
    0.1005629997531914
   ],
   "class": 1.0,
   "name": "point5"
  },
  {
   "coordinates": [
    0.14801077664809037,
    0.07405166445453641
   ],
   "class": 1.0,
   "name": "point6"
  },
  {
   "coordinates": [
    0.12612674387481312,
    0.4673654555087587
   ],
   "class": 1.0,
   "name": "point7"
  },
  {
   "coordinates": [
    0.5881286509051017,
    0.5868295711846714
   ],
   "class": 2.0,
   "name": "point8"
  },
  {
   "coordinates": [
    0.4271644033154517,
    0.062571110533443
   ],
   "class": 2.0,
   "name": "point9"
  },
  {
   "coordinates": [
    0.4164713947480362,
    0.48576016128058525
   ],
   "class": 2.0,
   "name": "point10"
  },
  {
   "coordinates": [
    0.547303320338351,
    0.7799192929377421
   ],
   "class": 2.0,
   "name": "point11"
  },
  {
   "coordinates": [
    0.4903781162180705,
    0.6628009917042995
   ],
   "class": 2.0,
   "name": "point12"
  },
  {
   "coordinates": [
    0.42989915223925756,
    0.3036261657709534
   ],
   "class": 2.0,
   "name": "point13"
  },
  {
   "coordinates": [
    0.36032869878386015,
    0.22914590159877327
   ],
   "class": 2.0,
   "name": "point14"
  },
  {
   "coordinates": [
    0.7559653238871751,
    0.027425290718747747
   ],
   "class": 3.0,
   "name": "point15"
  },
  {
   "coordinates": [
    0.7724830365498894,
    0.8891404382515125
   ],
   "class": 3.0,
   "name": "point16"
  },
  {
   "coordinates": [
    0.5962628684911377,
    0.5841362913677252
   ],
   "class": 3.0,
   "name": "point17"
  },
  {
   "coordinates": [
    0.739457003436787,
    0.3636533179693472
   ],
   "class": 3.0,
   "name": "point18"
  },
  {
   "coordinates": [
    0.7025263083704706,
    0.12587631401992147
   ],
   "class": 3.0,
   "name": "point19"
  },
  {
   "coordinates": [
    0.6482760127148899,
    0.08905396677270637
   ],
   "class": 3.0,
   "name": "point20"
  },
  {
   "coordinates": [
    0.6515208841409371,
    0.5856279359352301
   ],
   "class": 3.0,
   "name": "point21"
  }
 ],
 "m_d": [
  0.12612674387481312,
  0.027425290718747747
 ],
 "M_d": [
  0.7724830365498894,
  0.8891404382515125
 ]
}